pyotdr/__init__.py
pyotdr/cksum.py
pyotdr/datapts.py
pyotdr/dump.py
pyotdr/fxdparams.py
pyotdr/genparams.py
pyotdr/keyevents.py
pyotdr/main.py
pyotdr/mapblock.py
pyotdr/parts.py
pyotdr/read.py
pyotdr/supparams.py
tests/__init__.py
tests/test_cksum.py
tests/test_map.py
tests/test_parts.py
tests/test_read.py
pyotdr-2.1.1.dist-info/LICENSE
pyotdr-2.1.1.dist-info/METADATA
pyotdr-2.1.1.dist-info/WHEEL
pyotdr-2.1.1.dist-info/entry_points.txt
pyotdr-2.1.1.dist-info/top_level.txt
pyotdr-2.1.1.dist-info/RECORD
