Metadata-Version: 2.1
Name: pyotdr
Version: 2.1.1
Summary: A simple OTDR SOR file parser
Home-page: https://github.com/sid5432/pyOTDR
Author: Sidney Li, Rémi Desgrange
Author-email: sidneyli5432@gmail.com, remi+pyotdr@desgran.ge
Keywords: SR-4731 reflectometer Telcordia OTDR SOR
Classifier: Development Status :: 4 - Beta
Classifier: Intended Audience :: Telecommunications Industry
Classifier: Topic :: Utilities
Classifier: License :: OSI Approved :: GNU General Public License v3 or later (GPLv3+)
Classifier: Programming Language :: Python :: 3
Classifier: Programming Language :: Python :: 3.6
Classifier: Programming Language :: Python :: 3.7
Classifier: Programming Language :: Python :: 3.8
Classifier: Programming Language :: Python :: 3.9
Classifier: Programming Language :: Python :: 3.10
Classifier: Programming Language :: Python :: 3.11
Classifier: Programming Language :: Python :: 3.12
License-File: LICENSE
Requires-Dist: crcmod
Requires-Dist: dicttoxml
